fastvalidate/__init__.py
fastvalidate/pydantic.py
fastvalidate/rule_abstract.py
fastvalidate/validator.py
fastvalidate/rules/__init__.py
fastvalidate/rules/alpha.py
fastvalidate/rules/alpha_dash.py
fastvalidate/rules/alpha_num.py
fastvalidate/rules/boolean.py
fastvalidate/rules/choice.py
fastvalidate/rules/comparison.py
fastvalidate/rules/date.py
fastvalidate/rules/dict.py
fastvalidate/rules/email.py
fastvalidate/rules/len.py
fastvalidate/rules/list.py
fastvalidate/rules/max.py
fastvalidate/rules/min.py
fastvalidate/rules/network.py
fastvalidate/rules/numeric.py
fastvalidate/rules/password.py
fastvalidate/rules/regex.py
fastvalidate/rules/required.py
fastvalidate/rules/url.py
fastvalidate/rules/uuid.py
fastvalidate-1.0.0.dist-info/LICENSE.md
fastvalidate-1.0.0.dist-info/METADATA
fastvalidate-1.0.0.dist-info/WHEEL
fastvalidate-1.0.0.dist-info/top_level.txt
fastvalidate-1.0.0.dist-info/RECORD
