Metadata-Version: 2.1
Name: fastvalidate
Version: 1.0.0
Summary: Easy validation for python
Home-page: https://github.com/mojtabaahn/fast-validate
Author: Mojtabaa Habibain
Author-email: mojtabaa.hn@gmail.com
Classifier: Programming Language :: Python :: 3
Classifier: License :: OSI Approved :: MIT License
Classifier: Operating System :: OS Independent
Requires-Python: >=3.6
License-File: LICENSE.md
